{
    "data": {
        "type": "Evoluci\u00f3n de la demanda",
        "id": "dem1",
        "attributes": {
            "title": "Evoluci\u00f3n de la demanda",
            "last-update": "2021-01-12T10:19:24.000+01:00",
            "description": null
        },
        "meta": {
            "cache-control": {
                "cache": "HIT",
                "expireAt": "2024-11-27T15:31:08"
            }
        }
    },
    "included": [
        {
            "type": "Demanda",
            "id": "10339",
            "groupId": null,
            "attributes": {
                "title": "Demanda",
                "description": null,
                "color": "#ffea00",
                "type": null,
                "magnitude": null,
                "composite": false,
                "last-update": "2021-01-19T19:56:23.000+01:00",
                "values": [
                    {
                        "value": 826921.959,
                        "percentage": 1,
                        "datetime": "2020-01-01T00:00:00.000+01:00"
                    },
                    {
                        "value": 710409.485,
                        "percentage": 1,
                        "datetime": "2020-02-01T00:00:00.000+01:00"
                    },
                    {
                        "value": 748455.972,
                        "percentage": 1,
                        "datetime": "2020-03-01T00:00:00.000+01:00"
                    },
                    {
                        "value": 630962.979,
                        "percentage": 1,
                        "datetime": "2020-04-01T00:00:00.000+02:00"
                    },
                    {
                        "value": 700712.044,
                        "percentage": 1,
                        "datetime": "2020-05-01T00:00:00.000+02:00"
                    },
                    {
                        "value": 751296.944,
                        "percentage": 1,
                        "datetime": "2020-06-01T00:00:00.000+02:00"
                    },
                    {
                        "value": 909611.101,
                        "percentage": 1,
                        "datetime": "2020-07-01T00:00:00.000+02:00"
                    },
                    {
                        "value": 904273.955,
                        "percentage": 1,
                        "datetime": "2020-08-01T00:00:00.000+02:00"
                    },
                    {
                        "value": 773862.263,
                        "percentage": 1,
                        "datetime": "2020-09-01T00:00:00.000+02:00"
                    },
                    {
                        "value": 737168.266,
                        "percentage": 1,
                        "datetime": "2020-10-01T00:00:00.000+02:00"
                    },
                    {
                        "value": 714052.423,
                        "percentage": 1,
                        "datetime": "2020-11-01T00:00:00.000+01:00"
                    },
                    {
                        "value": 796790.727,
                        "percentage": 1,
                        "datetime": "2020-12-01T00:00:00.000+01:00"
                    }
                ]
            }
        }
    ]
}